transformers_embedder/__init__.py
transformers_embedder/embedder.py
transformers_embedder/tokenizer.py
transformers_embedder/utils.py
transformers_embedder/modules/__init__.py
transformers_embedder/modules/encoder.py
transformers_embedder/modules/scalar_mix.py
transformers_embedder-3.0.11.dist-info/METADATA
transformers_embedder-3.0.11.dist-info/WHEEL
transformers_embedder-3.0.11.dist-info/top_level.txt
transformers_embedder-3.0.11.dist-info/RECORD
