Metadata-Version: 2.1
Name: transformers-embedder
Version: 3.0.11
Summary: Word level transformer based embeddings
Home-page: https://github.com/Riccorl/transformers-embedder
Author: Riccardo Orlando
Author-email: orlandoricc@gmail.com
License: Apache
Keywords: NLP deep learning transformer pytorch BERT google subtoken wordpieces embeddings
Classifier: Programming Language :: Python :: 3
Classifier: License :: OSI Approved :: Apache Software License
Classifier: Operating System :: OS Independent
Requires-Python: >=3.6
Requires-Dist: transformers (<4.30,>=4.14)
Provides-Extra: all
Requires-Dist: torch (<2.1,>=1.5) ; extra == 'all'
Provides-Extra: docs
Requires-Dist: mkdocs-material ; extra == 'docs'
Provides-Extra: torch
Requires-Dist: torch (<2.1,>=1.5) ; extra == 'torch'
